pyclipse/__main__.py
pyclipse/dataset.py
pyclipse/evaluate.py
pyclipse/io.py
pyclipse/label.py
pyclipse/torch_dataset.py
pyclipse-0.0.1.dist-info/LICENSE
pyclipse-0.0.1.dist-info/METADATA
pyclipse-0.0.1.dist-info/WHEEL
pyclipse-0.0.1.dist-info/entry_points.txt
pyclipse-0.0.1.dist-info/top_level.txt
pyclipse-0.0.1.dist-info/RECORD
